{
  "main": {
    "id": "5324373015726ba8",
    "type": "split",
    "children": [
      {
        "id": "4509724f8bf84da7",
        "type": "tabs",
        "children": [
          {
            "id": "e7a7b303c61786dc",
            "type": "leaf",
            "state": {
              "type": "markdown",
              "state": {
                "file": "OSDev/Basics/Introduction.md",
                "mode": "source",
                "source": false
              },
              "icon": "lucide-file",
              "title": "Introduction"
            }
          }
        ]
      }
    ],
    "direction": "vertical"
  },
  "left": {
    "id": "fd964f6f0a559723",
    "type": "mobile-drawer",
    "children": [
      {
        "id": "da310c3bd5a67739",
        "type": "leaf",
        "state": {
          "type": "file-explorer",
          "state": {
            "sortOrder": "alphabetical",
            "autoReveal": false
          },
          "icon": "lucide-folder-closed",
          "title": "Files"
        }
      },
      {
        "id": "eee3a52b2db1ed30",
        "type": "leaf",
        "state": {
          "type": "search",
          "state": {
            "query": "",
            "matchingCase": false,
            "explainSearch": false,
            "collapseAll": false,
            "extraContext": false,
            "sortOrder": "alphabetical"
          },
          "icon": "lucide-search",
          "title": "Search"
        }
      },
      {
        "id": "d9e12a3cd346b0c0",
        "type": "leaf",
        "state": {
          "type": "tag",
          "state": {
            "sortOrder": "frequency",
            "useHierarchy": true,
            "showSearch": false,
            "searchQuery": ""
          },
          "icon": "lucide-tags",
          "title": "Tags"
        }
      },
      {
        "id": "e0e80df53417a81e",
        "type": "leaf",
        "state": {
          "type": "bookmarks",
          "state": {},
          "icon": "lucide-bookmark",
          "title": "Bookmarks"
        }
      }
    ],
    "currentTab": 0
  },
  "right": {
    "id": "f5e383f150fe1832",
    "type": "mobile-drawer",
    "children": [
      {
        "id": "447b9e53f2f47d51",
        "type": "leaf",
        "state": {
          "type": "backlink",
          "state": {
            "file": "OSDev/Basics/Introduction.md",
            "collapseAll": false,
            "extraContext": false,
            "sortOrder": "alphabetical",
            "showSearch": false,
            "searchQuery": "",
            "backlinkCollapsed": false,
            "unlinkedCollapsed": true
          },
          "icon": "links-coming-in",
          "title": "Backlinks"
        }
      },
      {
        "id": "6cd672faf9664200",
        "type": "leaf",
        "state": {
          "type": "outgoing-link",
          "state": {
            "file": "Maths/Identity.md",
            "linksCollapsed": false,
            "unlinkedCollapsed": true
          },
          "icon": "links-going-out",
          "title": "Outgoing links"
        }
      },
      {
        "id": "8b053419d93d368f",
        "type": "leaf",
        "state": {
          "type": "outline",
          "state": {
            "file": "Maths/Identity.md",
            "followCursor": false,
            "showSearch": false,
            "searchQuery": ""
          },
          "icon": "lucide-list",
          "title": "Outline"
        }
      },
      {
        "id": "c954d837212cc296",
        "type": "leaf",
        "state": {
          "type": "calendar",
          "state": {},
          "icon": "calendar-with-checkmark",
          "title": "Calendar"
        }
      }
    ],
    "currentTab": 0
  },
  "left-ribbon": {
    "hiddenItems": {
      "switcher:Open quick switcher": false,
      "graph:Open graph view": false,
      "canvas:Create new canvas": false,
      "daily-notes:Open today's daily note": false,
      "templates:Insert template": false,
      "command-palette:Open command palette": false,
      "homepage:Open homepage": false,
      "obsidian-excalidraw-plugin:New drawing": false,
      "table-editor-obsidian:Advanced Tables Toolbar": false
    }
  },
  "active": "e7a7b303c61786dc",
  "lastOpenFiles": [
    "OSDev/OSDev.md",
    "OSDev/Basics/Introduction.md",
    "OSDev/Basics",
    "Home.md",
    "Maths/Equations.md",
    "OSDev",
    "Diary/2025/April/Friday - 4th Apr 2025.md",
    "Diary/2025/April",
    "Diary/2025",
    "Demo.md",
    "Diary/Thursday - 3rd Apr 2025.md",
    "Zig/Overview.md",
    "Templates/Daily Note.md",
    "Maths/Identity.md",
    "Diary/Wednesday - 2nd Apr 2025.md"
  ]
}